ANNOUNCE
AUTHORS
CHANGES
LICENSE
MANIFEST.in
README.rst
requirements.txt
setup.py
bits/__init__.py
bits/bits.py
bits/carver.py
bits/const.py
bits/sampler.py
bits/structs.py
bits/writer.py
bits/helpers/__init__.py
bits/helpers/fields.py
bits/helpers/tools.py
bits_parser.egg-info/PKG-INFO
bits_parser.egg-info/SOURCES.txt
bits_parser.egg-info/dependency_links.txt
bits_parser.egg-info/not-zip-safe
bits_parser.egg-info/requires.txt
bits_parser.egg-info/top_level.txt
scripts/bits_parser