Metadata-Version: 1.1
Name: bits-parser
Version: 1.0.0
Summary: bits_parser
Home-page: UNKNOWN
Author: ANSSI-INM
Author-email: contact@ssi.gouv.fr
License: MIT
Platform: any
Classifier: Development Status :: 4 - Beta
Classifier: Programming Language :: Python
Classifier: Programming Language :: Python :: 3
Classifier: Programming Language :: Python :: 3.5
Classifier: Programming Language :: Python :: 3.6
